azure/mgmt/botservice/__init__.py
azure/mgmt/botservice/_azure_bot_service.py
azure/mgmt/botservice/_configuration.py
azure/mgmt/botservice/_version.py
azure/mgmt/botservice/aio/__init__.py
azure/mgmt/botservice/aio/_azure_bot_service.py
azure/mgmt/botservice/aio/_configuration.py
azure/mgmt/botservice/aio/operations/__init__.py
azure/mgmt/botservice/aio/operations/_bot_connection_operations.py
azure/mgmt/botservice/aio/operations/_bots_operations.py
azure/mgmt/botservice/aio/operations/_channels_operations.py
azure/mgmt/botservice/aio/operations/_direct_line_operations.py
azure/mgmt/botservice/aio/operations/_host_settings_operations.py
azure/mgmt/botservice/aio/operations/_operations.py
azure/mgmt/botservice/models/__init__.py
azure/mgmt/botservice/models/_azure_bot_service_enums.py
azure/mgmt/botservice/models/_models.py
azure/mgmt/botservice/models/_models_py3.py
azure/mgmt/botservice/operations/__init__.py
azure/mgmt/botservice/operations/_bot_connection_operations.py
azure/mgmt/botservice/operations/_bots_operations.py
azure/mgmt/botservice/operations/_channels_operations.py
azure/mgmt/botservice/operations/_direct_line_operations.py
azure/mgmt/botservice/operations/_host_settings_operations.py
azure/mgmt/botservice/operations/_operations.py
azure_mgmt_botservice-1.0.0.dist-info/METADATA
azure_mgmt_botservice-1.0.0.dist-info/WHEEL
azure_mgmt_botservice-1.0.0.dist-info/top_level.txt
azure_mgmt_botservice-1.0.0.dist-info/RECORD
